{
	"a": [
			"pepeHansA",
			"testA",
			"blepA",
			"dingdongA"
		]
	,
	"b": [
			"pepeHansBB",
			"testBB",
			"blepBB",
			"dingdongB"
		]
	,
	"c": [
			"pepeHansC",
			"testC",
			"blepC",
			"dingdongC"
		]
	,
	"d": [
			"pepeHansD",
			"testD",
			"blepD",
			"dingdongD"
		]
	,
	"e": [
			"pepeHansE",
			"testE",
			"blepE",
			"dingdongE"
		]
	,
	"f": [
			"pepeHansF",
			"testF",
			"blepF",
			"dingdongF"
		]
	,
	"g": [
			"pepeHansG",
			"testG",
			"blepG",
			"dingdongG"
		]
	,
	"h": [
			"pepeHansH",
			"testH",
			"blepH",
			"dingdongH"
		]
	,
}